m14-0.1-py3.7-nspkg.pth
m14/default/__init__.py
m14-0.1.dist-info/METADATA
m14-0.1.dist-info/WHEEL
m14-0.1.dist-info/namespace_packages.txt
m14-0.1.dist-info/top_level.txt
m14-0.1.dist-info/RECORD
