Metadata-Version: 2.1
Name: m14
Version: 0.1
Summary: locate default directories for m14 projects
Home-page: UNKNOWN
Author: frozflame
Author-email: frozflame@outlook.com
License: GNU General Public License (GPL)
Keywords: m14
Platform: UNKNOWN
Classifier: Programming Language :: Python
Classifier: Programming Language :: Python :: 2
Classifier: Programming Language :: Python :: 2.7
Classifier: Programming Language :: Python :: 3
Classifier: Programming Language :: Python :: 3.0
Classifier: Programming Language :: Python :: 3.1
Classifier: Programming Language :: Python :: 3.2
Classifier: Programming Language :: Python :: 3.3
Classifier: Programming Language :: Python :: 3.4
Classifier: Programming Language :: Python :: 3.5
Classifier: Programming Language :: Python :: 3.6
Requires-Dist: joker
Requires-Dist: pyyaml
